antisafelinks/__init__.py
antisafelinks/safelink_decoder.py
antisafelinks-1.1.1.dist-info/LICENSE
antisafelinks-1.1.1.dist-info/METADATA
antisafelinks-1.1.1.dist-info/WHEEL
antisafelinks-1.1.1.dist-info/entry_points.txt
antisafelinks-1.1.1.dist-info/top_level.txt
antisafelinks-1.1.1.dist-info/RECORD
