Metadata-Version: 2.1
Name: antisafelinks
Version: 1.1.1
Summary: Removes the Microsoft SafeLinks from emails or Maildir folders
Author-email: Benito Marcote <benito.marcote@icloud.com>
Project-URL: Homepage, https://github.com/bmarcote/antisafelinks
Project-URL: Bug Tracker, https://github.com/bmarcote/antisafelinks/issues
Classifier: Programming Language :: Python :: 3
Classifier: License :: OSI Approved :: GNU General Public License v3 or later (GPLv3+)
Classifier: Operating System :: POSIX
Classifier: Environment :: Console
Classifier: Development Status :: 4 - Beta
Requires-Python: >=3.9
License-File: LICENSE
